gigalixir/__init__.py
gigalixir/api_exception.py
gigalixir/api_key.py
gigalixir/api_session.py
gigalixir/app.py
gigalixir/app_activity.py
gigalixir/auth.py
gigalixir/canary.py
gigalixir/config.py
gigalixir/database.py
gigalixir/domain.py
gigalixir/free_database.py
gigalixir/git.py
gigalixir/invoice.py
gigalixir/log_drain.py
gigalixir/mfa.py
gigalixir/netrc.py
gigalixir/observer.py
gigalixir/payment_method.py
gigalixir/permission.py
gigalixir/presenter.py
gigalixir/release.py
gigalixir/shell.py
gigalixir/signup.py
gigalixir/ssh_key.py
gigalixir/usage.py
gigalixir/user.py
gigalixir/openers/__init__.py
gigalixir/openers/darwin.py
gigalixir/openers/linux.py
gigalixir/openers/windows.py
gigalixir/routers/__init__.py
gigalixir/routers/darwin.py
gigalixir/routers/linux.py
gigalixir/routers/windows.py
gigalixir-1.15.0.dist-info/licenses/LICENSE
gigalixir-1.15.0.dist-info/METADATA
gigalixir-1.15.0.dist-info/WHEEL
gigalixir-1.15.0.dist-info/entry_points.txt
gigalixir-1.15.0.dist-info/top_level.txt
gigalixir-1.15.0.dist-info/RECORD
